{
  "id": 14,
  "title": "Blocking Access if Not Logged In",
  "description": "How to prevent users from accessing pages unless they are logged in.",
  "content": "To keep certain pages private, check if the user is logged in before showing the page. If not, redirect them to the login page.",
  "code_snippets": {
    "flask": { "language": "python", "code": "if 'user_id' not in session:\n    return redirect('/login')" },
    "express": { "language": "javascript", "code": "if (!req.session.userId) {\n  res.redirect('/login');\n}" },
    "django": { "language": "python", "code": "if not request.session.get('user_id'):\n    return redirect('/login')" }
  },
  "next": 15
}
